fast_neptune/__init__.py
fast_neptune/_nbdev.py
fast_neptune/core.py
fast_neptune-0.0.3.dist-info/METADATA
fast_neptune-0.0.3.dist-info/RECORD
fast_neptune-0.0.3.dist-info/WHEEL
fast_neptune-0.0.3.dist-info/entry_points.txt
fast_neptune-0.0.3.dist-info/top_level.txt
nbdev_template/__init__.py
nbdev_template/_nbdev.py
