Metadata-Version: 2.1
Name: fast-neptune
Version: 0.0.3
Summary: NeptuneML wrapper to quickly record data about experiments
Home-page: https://github.com/DanyWind/fast_neptune
Author: Daniel Huynh
Author-email: daniel.quoc.huynh@gmail.com
License: Apache Software License 2.0
Keywords: netpuneml experiments
Platform: UNKNOWN
Classifier: Development Status :: 3 - Alpha
Classifier: Intended Audience :: Developers
Classifier: License :: OSI Approved :: Apache Software License
Classifier: Natural Language :: English
Classifier: Programming Language :: Python :: 3.6
Classifier: Programming Language :: Python :: 3.7
Classifier: Programming Language :: Python :: 3.8
Requires-Python: >=3.6
Requires-Dist: psutil
Requires-Dist: neptune-client
Requires-Dist: nbdev
Requires-Dist: pipreqs
